py_node_collector/__init__.py
py_node_collector/_collector.cpython-310-x86_64-linux-gnu.so
py_node_collector/_collector.cpython-311-x86_64-linux-gnu.so
py_node_collector/_collector.cpython-312-x86_64-linux-gnu.so
py_node_collector/_collector.cpython-38-x86_64-linux-gnu.so
py_node_collector/_collector.cpython-39-x86_64-linux-gnu.so
py_node_collector/build.py
py_node_collector/collector.py
py_node_collector/go.py
py_node_collector-0.0.3.dist-info/LICENSE
py_node_collector-0.0.3.dist-info/METADATA
py_node_collector-0.0.3.dist-info/WHEEL
py_node_collector-0.0.3.dist-info/top_level.txt
py_node_collector-0.0.3.dist-info/RECORD
