Metadata-Version: 2.1
Name: py-node-collector
Version: 0.0.3
Summary: Python wrapper for Prometheus Node Collector https://github.com/shadowy-pycoder/go-node-collector
Home-page: https://github.com/shadowy-pycoder/py-node-collector
Author: shadowy-pycoder
Author-email: shadowy-pycoder@example.com
License: UNKNOWN
Keywords: prometheus,metrics,prometheus-collector,prometheus-node-exporter
Platform: Linux
Classifier: Programming Language :: Python :: 3
Classifier: Programming Language :: Python :: 3.8
Classifier: Programming Language :: Python :: 3.9
Classifier: Programming Language :: Python :: 3.10
Classifier: Programming Language :: Python :: 3.11
Classifier: Programming Language :: Python :: 3.12
Classifier: License :: OSI Approved :: MIT License
Classifier: Operating System :: POSIX :: Linux
